pygame_magics/__init__.py
pygame_magics/camera/__init__.py
pygame_magics/camera/camera.py
pygame_magics/entities/__init__.py
pygame_magics/entities/enemy.py
pygame_magics/entities/experience_orb.py
pygame_magics/entities/magic_bolt.py
pygame_magics/entities/player.py
pygame_magics/entities/player_stats.py
pygame_magics/entities/samples.py
pygame_magics/entities/singleton.py
pygame_magics-0.6.0.dist-info/METADATA
pygame_magics-0.6.0.dist-info/WHEEL
pygame_magics-0.6.0.dist-info/top_level.txt
pygame_magics-0.6.0.dist-info/RECORD
