Metadata-Version: 2.1
Name: pygame-magics
Version: 0.6.0
Summary: Magic survival funcs
Home-page: https://github.com/MCtop4ik/pygame-magics
Author: MCtop4ik
Author-email: senyaza@mail.ru
Classifier: Development Status :: 3 - Alpha
Classifier: Intended Audience :: Developers
Classifier: License :: OSI Approved :: MIT License
Classifier: Programming Language :: Python :: 3
Classifier: Programming Language :: Python :: 3.6
Classifier: Programming Language :: Python :: 3.7
Classifier: Programming Language :: Python :: 3.8
Classifier: Programming Language :: Python :: 3.9
Requires-Python: >=3.6
Requires-Dist: pygame
